<Game>
	<Name>Appare Gateball (Japan)</Name>
	<plot>Overview:Appare! Gateball is a sports game developed by Westone and published by Hudson for the PC Engine (TurboGrafx-16) platform. Appare! Gateball was never released outside of Japan.On July 24th, 2007 Appare! Gateball was released on the Japanese Wii Virtual Console.Gameplay:Appare! Gateball is a game of croquet. The object of the game is to hit the ball through the small gates on the ground in a certain order in the least amount of hits possible.To hit the ball the shot must first be lined up and then set. Once the shot has been set then the power of the shot must also be set. To set the power the player must stop a cursor that is traveling left and right continuously.</plot>
	<releasedate>22/12/1988</releasedate>
	<genre>Sports, Miscellaneous</genre>
	<Developer>West One</Developer>
	<thegamesdb_id>20231</thegamesdb_id>
	<gamefaqs_url>http://www.gamefaqs.com/tg16/588893-appare-gateball</gamefaqs_url>
	<mobygames_url>http://www.mobygames.com/game/turbo-grafx/appare-gateball</mobygames_url>
	<giantbomb_url>http://www.giantbomb.com/appare-gateball/3030-37327/</giantbomb_url>
	<boxart1>http://thegamesdb.net/banners/boxart/original/front/20231-1.jpg</boxart1>
	<snapshot1>http://static.giantbomb.com/uploads/scale_large/2/23093/2801400-apparegateball001.jpg</snapshot1>
	<snapshot2>http://static.giantbomb.com/uploads/scale_large/2/23093/2801399-appare%21_gateball_%28j%29-004.jpg</snapshot2>
	<snapshot3>http://static.giantbomb.com/uploads/scale_large/2/23093/2801398-appare%21_gateball_%28j%29-003.jpg</snapshot3>
	<snapshot4>http://static.giantbomb.com/uploads/scale_large/2/23093/2801397-appare%21_gateball_%28j%29-002.jpg</snapshot4>
	<snapshot5>http://static.giantbomb.com/uploads/scale_large/2/23093/2801396-appare%21_gateball_%28j%29-001.jpg</snapshot5>
	<snapshot6>http://static.giantbomb.com/uploads/scale_large/10/103881/2112942-6.png</snapshot6>
	<snapshot7>http://static.giantbomb.com/uploads/scale_large/10/103881/2112941-5.png</snapshot7>
	<snapshot8>http://static.giantbomb.com/uploads/scale_large/10/103881/2112940-4.png</snapshot8>
	<snapshot9>http://static.giantbomb.com/uploads/scale_large/10/103881/2112939-3.png</snapshot9>
	<snapshot10>http://static.giantbomb.com/uploads/scale_large/10/103881/2112938-2.png</snapshot10>
</game>