<Game>
	<Name>PANG- Magical Michael</Name>
	<ReleaseDate>2010-09-17T00:00:00-07:00</ReleaseDate>
	<Plot>Michael, an aspiring young magician, has failed an experiment - leading to dire consequences. Balloons have been dispersed, causing trouble to landmarks and cities all around the world. Now, Michael must travel the globe to destroy these balloons and clean up his mistake, before it's too late. Celebrating 21 years since the original game blasted onto the arcade scene, Pang returns with all the addictive gameplay that made it so popular, now on the Nintendo DS. With the same simple premise and addictive gameplay, Pang: Magical Michael continues to define what lead the series to critical acclaim, cementing its position as one of the most cherished properties in videogame history.</Plot>
	<VideoURL>K5vTOyFjcM0</VideoURL>
	<boxart1>http://images.launchbox-app.com/aac7237b-2ff3-498f-bcb7-f5d2d9a850eb.jpg</boxart1>
	<clearlogo1>http://images.launchbox-app.com/f7b76aaa-271f-4151-a90e-0c406ae035fd.png</clearlogo1>
	<snapshot1>http://images.launchbox-app.com/3bf4a39a-c431-4949-a2d0-7bc096f3b879.jpg</snapshot1>
	<WikipediaURL>https://en.wikipedia.org/wiki/Pang:_Magical_Michael</WikipediaURL>
	<Genre>Action; Platform; Puzzle</Genre>
	<Developer>Mitchell Corporation</Developer>
	<Publisher>Rising Star Games</Publisher>
</game>