<Game>
	<Name>Rock Band 3</Name>
	<ReleaseDate>2010-10-26T00:00:00-07:00</ReleaseDate>
	<Plot>Get ready to take the ultimate music experience on the road with Rock Band® 3, the next major installment in the Rock Band series; now available for the first time on the Nintendo DS. Featuring innovative game modes, Rock Band 3 will change the way fans think about and play music games on the go.</Plot>
	<nPlayers>2</nPlayers>
	<boxback1>http://images.launchbox-app.com/ee6d9f2d-2b33-4835-a9c5-61d17ba130a7.jpg</boxback1>
	<boxart1>http://images.launchbox-app.com/fbaacb4a-f166-490c-a385-4767bd5b5a0c.jpg</boxart1>
	<boxart2>http://images.launchbox-app.com/fd659f69-cca2-458e-aecf-d9def6abebb7.jpg</boxart2>
	<clearlogo1>http://images.launchbox-app.com/ec37dce4-9fa6-4d86-94b5-c6c38e6237a1.png</clearlogo1>
	<snapshot1>http://images.launchbox-app.com/54acb277-3329-47a9-8a90-819a85601d99.jpg</snapshot1>
	<snapshot2>http://images.launchbox-app.com/aeeb9c54-1f23-47d3-a303-0b0a35f65086.jpg</snapshot2>
	<snapshot3>http://images.launchbox-app.com/63d08b5c-70fe-4731-b6c9-e73d8cf11c15.jpg</snapshot3>
	<WikipediaURL>https://en.wikipedia.org/wiki/Rock_Band_3#Nintendo_DS_version</WikipediaURL>
	<ESRB>E10+ - Everyone 10+</ESRB>
	<Genre>Music</Genre>
	<Developer>Harmonix Music Systems</Developer>
	<Publisher>MTV Games</Publisher>
</game>