<Game>
	<Name>Shrek the Third</Name>
	<ReleaseDate>2007-05-08T00:00:00-07:00</ReleaseDate>
	<Plot>In Shrek the Third, players journey as Shrek and his friends to save Far, Far Away in a twisted fairytale adventure from the movie and beyond. Assuming the roles of Shrek, Puss-in-Boots and newcomer Artie, players journey beyond Far Far Away with the help of Merlin's magic wand. The Nintendo DS game tells the story of how Shrek and friends must work together to solve puzzles and defeat enemies while overcoming the band of villains that Prince Charming has sent out to capture Shrek.</Plot>
	<nPlayers>3</nPlayers>
	<boxback1>http://images.launchbox-app.com/e8c8223e-fd94-432d-ad47-0a9a7ab85795.png</boxback1>
	<boxart1>http://images.launchbox-app.com/fcc20625-1818-45fa-aa28-4a12a53f3b0e.png</boxart1>
	<clearlogo1>http://images.launchbox-app.com/fa3e8f55-6330-4a2a-8608-4aae68311024.png</clearlogo1>
	<clearlogo2>http://images.launchbox-app.com/d8961d48-be03-4ed9-8d78-cf83326e7016.png</clearlogo2>
	<ESRB>E - Everyone</ESRB>
	<Genre>Action</Genre>
	<Developer>Vicarious Visions</Developer>
	<Publisher>Activision</Publisher>
</game>