<Game>
	<Name>Tetris Party Deluxe</Name>
	<ReleaseDate>2010-05-25T00:00:00-07:00</ReleaseDate>
	<Plot>You know Tetris, but do you know how to party? Tetris Party Deluxe builds on the previously released Tetris Party for WiiWare by adding new modes and features to enrich the overall gameplay experience for both Wii and Nintendo DS. With more than 20 exciting modes, online battles, and multiplayer fun for groups of friends and family, Tetris Party Deluxe is a must-have for Tetris and puzzle fans.</Plot>
	<nPlayers>4</nPlayers>
	<VideoURL>dYor9uSTRyI</VideoURL>
	<banner1>http://images.launchbox-app.com/0f3f0e9e-6d1c-410c-b206-b4a55a7f6673.jpg</banner1>
	<boxback1>http://images.launchbox-app.com/6849113d-bd47-46f9-89e3-9e1201628aa7.jpg</boxback1>
	<boxart1>http://images.launchbox-app.com/8793e92b-6f86-4722-9404-dafce5c47f7e.jpg</boxart1>
	<clearlogo1>http://images.launchbox-app.com/753e9b7b-8873-4f35-8880-48ad6f43bf18.png</clearlogo1>
	<fanart1>http://images.launchbox-app.com/717054ab-d033-48aa-84c6-a9befc5264e6.jpg</fanart1>
	<fanart2>http://images.launchbox-app.com/942a8142-1b7e-4fb0-bce6-835bd0b0c883.jpg</fanart2>
	<fanart3>http://images.launchbox-app.com/368fcc3b-c7e9-46e8-9bb0-1ecf8c64459e.jpg</fanart3>
	<fanart4>http://images.launchbox-app.com/097f4e47-0dc2-4fad-8fca-52b6dfebf416.jpg</fanart4>
	<fanart5>http://images.launchbox-app.com/3db6ef4f-af2e-4bd1-8cba-7cfe15ac5058.jpg</fanart5>
	<snapshot1>http://images.launchbox-app.com/5284e766-b118-49c0-b702-79845d3bcb92.jpg</snapshot1>
	<snapshot2>http://images.launchbox-app.com/49a36c7a-790c-4a4b-b446-e9f011ef4f0e.jpg</snapshot2>
	<snapshot3>http://images.launchbox-app.com/f1c4f3e6-609a-4fee-9a6b-22555faaf7ed.jpg</snapshot3>
	<snapshot4>http://images.launchbox-app.com/aa64275a-5ceb-4a53-ac8d-e691b9de50a2.jpg</snapshot4>
	<snapshot5>http://images.launchbox-app.com/87945a41-516b-4b76-8c79-d9c80ef5573b.jpg</snapshot5>
	<Rating>2.5</Rating>
	<ESRB>E - Everyone</ESRB>
	<Genre>Puzzle; Strategy</Genre>
	<Developer>Tetris Online, Inc</Developer>
	<Publisher>Majesco Games</Publisher>
</game>