<Game>
	<Name>Umihara Kawase Shun- Second Edition Kanzenban</Name>
	<ReleaseDate>2009-10-29T00:00:00-07:00</ReleaseDate>
	<Plot>Umihara Kawase Shun: Second Edition Kanzenban is an Action game, developed and published by Genterprise, which was released in Japan in 2009.</Plot>
	<boxback1>http://images.launchbox-app.com/85874492-bc3c-4b9b-b64a-8d15ccd9381d.jpg</boxback1>
	<boxart1>http://images.launchbox-app.com/6ce39948-af71-4588-a613-e70652d61f11.jpg</boxart1>
	<ESRB>Not Rated</ESRB>
	<Genre>Action; Platform</Genre>
	<Developer>Genterprise</Developer>
	<Publisher>Genterprise</Publisher>
</game>