<Game>
	<Name>Superstar Pro Wrestling (Japan)</Name>
	<plot>The game features 12 selectable WCW wrestlers.Ric FlairLex LugerMike RotundaKevin SullivanStingRicky SteamboatHawkAnimalSteve WilliamsEddie Gilbert</plot>
	<releasedate>31/3/1990</releasedate>
	<genre>Action, Fighting, Sports</genre>
	<Developer>Nichibutsu</Developer>
	<rating>10.0</rating>
	<thegamesdb_id>1391</thegamesdb_id>
	<gamefaqs_url>http://www.gamefaqs.com/nes/579519-super-star-pro-wrestling</gamefaqs_url>
	<giantbomb_url>http://www.giantbomb.com/wcw-world-championship-wrestling/3030-775/</giantbomb_url>
	<boxart1>http://i.imgur.com/rYIBzX4.jpg</boxart1>
	<boxart2>http://i.imgur.com/02fn8dd.jpg</boxart2>
</game>