<Game>
	<Name>Takeda Shingen 2 (Japan)</Name>
	<plot>You are SHINGEN, 16th century samurai warlord. This is the ultimate in war simulation games. With your skill as a strategist you develop your country into a mighty war machine. You control agriculture, mining and morale among your people. You must overcome typhoons, epidemics, mine cave-ins, as well as powerful enemies. Now, enter SHINGEN's dream of total domination. Riflemen, Lancers, Calvary and Ninja spies are waiting for your commands on 42 different battlefields. Only your skill shall determine victory or defeat!Cheat: 100 Gold Mines (Japanese Version)At the game menu, pick the second option from the second row. Then select the 1st option, choose 0000 and highlight "Yes" (first option). On controller 2, hold Left-Down + B and on controller 1, press A. If done right, the gold mines counter will increase to 100.Cheat: Get 10 Free LancersGo to the merchant and tap select 10 times, the screen should blink twice to confirm. You will recieve 10 free lancers.</plot>
	<releasedate>6/5/1990</releasedate>
	<genre>Strategy, Miscellaneous</genre>
	<Developer>Another</Developer>
	<rating>9.0</rating>
	<thegamesdb_id>1413</thegamesdb_id>
	<gamefaqs_url>http://www.gamefaqs.com/nes/587609-shingen-the-ruler</gamefaqs_url>
	<giantbomb_url>http://www.giantbomb.com/takeda-shingen/3030-39959/</giantbomb_url>
	<boxart1>http://i.imgur.com/S1q8bsW.jpg</boxart1>
	<boxart2>http://i.imgur.com/aLHs7Rl.jpg</boxart2>
	<snapshot1>http://i.imgur.com/2SVR76L.jpg</snapshot1>
	<snapshot2>http://i.imgur.com/jEnjP0i.jpg</snapshot2>
	<snapshot3>http://i.imgur.com/n5L3Or3.jpg</snapshot3>
	<snapshot4>http://i.imgur.com/bI4S5Pj.jpg</snapshot4>
	<snapshot5>http://i.imgur.com/mUDKaTM.jpg</snapshot5>
	<snapshot6>http://i.imgur.com/oNnAm1X.jpg</snapshot6>
	<snapshot7>http://i.imgur.com/ovloxum.jpg</snapshot7>
	<snapshot8>http://i.imgur.com/eYOIqnF.jpg</snapshot8>
	<snapshot9>http://i.imgur.com/uEhY9Lh.jpg</snapshot9>
	<snapshot10>http://i.imgur.com/M2kbSYJ.jpg</snapshot10>
</game>