<Game>
	<Name>Aero the Acro-Bat (Europe)</Name>
	<plot>Overview:Aero the Acro-Bat is a mascot platformer from Iguana Entertainment, the studio best known for creating NBA Jam and Turok that would later become Acclaim Studios Austin. Aero was the second game Iguana developed after the football game Super High Impact.Aero the Acro-Bat was released on the Genesis and Super Nintendo in late 1993 in both Europe and the US, and was later ported to the GBA in 2002, where it made its Japanese debut. The SNES version was placed on the Wii's Virtual Console in 2010 for US and European regions.Gameplay:The levels play out in typical 2D platforming style but in order to clear levels, the player must accomplish certain tasks so that the exit warp can be revealed. Those tasks include passing through hoops, stepping on platforms until they disappear, ride roller coasters, etc. There are 4 worlds with 5 levels in each one, and the levels are large, many of them containing awkwardly positioned spikes that kill instantly.Aero can attack enemies by shooting limited stars or by doing an aerial diagonal drill attack at his target (when he is in the air).Cheat: CodesOn the Start Screen, press C, A, Right, Left, C, A, Right Left. Then enter the following during gameplay:Cheat: CodesAt the continue screen after you lose all your lives, press Up, Down, Left, Right, Up, Down, Left, Right. This will give you a free continue. Do this every time you reach the continue screen.</plot>
	<releasedate>23/12/1993</releasedate>
	<genre>Action</genre>
	<Developer>SunSoft</Developer>
	<nplayers>1</nplayers>
	<rating>2.5</rating>
	<VideoURL>RB3oIq4OZ50</VideoURL>
	<thegamesdb_id>4237</thegamesdb_id>
	<gamefaqs_url>http://www.gamefaqs.com/genesis/586010-aero-the-acro-bat</gamefaqs_url>
	<mobygames_url>http://www.mobygames.com/game/genesis/aero-the-acro-bat</mobygames_url>
	<giantbomb_url>http://www.giantbomb.com/aero-the-acro-bat/3030-19337/</giantbomb_url>
	<boxart1>http://thegamesdb.net/banners/boxart/original/front/4237-2.png</boxart1>
	<boxback1>http://thegamesdb.net/banners/boxart/original/back/4237-1.png</boxback1>
	<media>http://www.mobygames.com/images/covers/l/17652-aero-the-acro-bat-genesis-media.jpg</media>
	<snapshot1>http://thegamesdb.net/banners/screenshots/4237-1.jpg</snapshot1>
	<snapshot2>http://thegamesdb.net/banners/screenshots/4237-2.jpg</snapshot2>
	<snapshot3>http://thegamesdb.net/banners/screenshots/4237-3.jpg</snapshot3>
	<snapshot4>http://thegamesdb.net/banners/screenshots/4237-4.jpg</snapshot4>
	<snapshot5>http://thegamesdb.net/banners/screenshots/4237-5.jpg</snapshot5>
	<snapshot6>http://thegamesdb.net/banners/screenshots/4237-6.jpg</snapshot6>
	<snapshot7>http://thegamesdb.net/banners/screenshots/4237-7.jpg</snapshot7>
	<snapshot8>http://thegamesdb.net/banners/screenshots/4237-8.jpg</snapshot8>
	<snapshot9>http://www.mobygames.com/images/shots/l/33500-aero-the-acro-bat-genesis-screenshot-title-screen.jpg</snapshot9>
	<snapshot10>http://www.mobygames.com/images/shots/l/33501-aero-the-acro-bat-genesis-screenshot-main-menu.jpg</snapshot10>
	<banner1>http://i.imgur.com/WmlP6t9.png</banner1>
	<clearlogo1>http://thegamesdb.net/banners/clearlogo/4237.png</clearlogo1>
	<Notes>You play as bat Aero, who have to stop the mad scientist Edgar Ektor, who is trying to rid the world of amusement and fun. So you jump through the circus-style levels, using different kinds of machines such as catapults, cannons, bubble machines, platforms, etc., collecting various power-ups such as cheese, soda, keys, clocks, etc. and avoiding lethal obstacles.</Notes>
	<VideoURL1>7y3dnbnhzIw</VideoURL1>
	<boxart2>http://images.launchbox-app.com/d4a60136-6fee-4c2e-92f1-d68df6e7ae2a.png</boxart2>
	<boxart3>http://images.launchbox-app.com/1ff4bcd0-b4d5-420e-b3ce-b9590d179aa7.png</boxart3>
	<clearlogo2>http://images.launchbox-app.com/99eb7748-70d0-415c-9d1e-43c7f2e1eb11.png</clearlogo2>
	<snapshot11>http://images.launchbox-app.com/f29d3d65-7e12-4784-9117-767a4038eb35.jpg</snapshot11>
	<snapshot12>http://images.launchbox-app.com/7d52a16b-305c-47f3-a3bb-ef43eb45d077.jpg</snapshot12>
	<snapshot13>http://images.launchbox-app.com/e901ed7e-512b-484b-93bc-ffed28b83f12.jpg</snapshot13>
	<snapshot14>http://images.launchbox-app.com/bb315fef-dc3e-4c8f-bacb-8d27ae08bc66.jpg</snapshot14>
	<snapshot15>http://images.launchbox-app.com/73c886ad-d941-44f6-ba2d-3284228f9936.jpg</snapshot15>
	<snapshot16>http://images.launchbox-app.com/5f933030-68e9-4935-b6cf-449592ee0216.jpg</snapshot16>
	<snapshot17>http://images.launchbox-app.com/ac5bda20-ec89-4568-8b30-1836d67f47fb.jpg</snapshot17>
	<snapshot18>http://images.launchbox-app.com/8a44a3df-1d3e-4f15-a3f1-a665cc581d62.jpg</snapshot18>
	<ESRB>Not Rated</ESRB>
	<Publisher>Sunsoft</Publisher>
</game>