<Game>
	<Name>Alisia Dragoon (Europe)</Name>
	<plot>Alisia Dragoon is the female protagonist of this fast-paced platform game. Alisia must destroy an evil demon and avenge her fathers death through eight stages. She has only one weapon to dispose of enemies: thunder magic. This magic is auto-aiming and can track multiple targets. However, the game is quite hard as the levels are loaded with fantasy-inspired monsters. Using thunder magic reduces a magic gauge, meaning you often have to wait for it to recharge. Once fully charged Alisia can unleash a massive rolling blast of lightning across the screen.During the game, you can improve your magic by picking up potions. There are also four monsters which accompany Alisia: Dragon Frye, Ball O'Fire, Thunder Raven and Boomerang Lizard. Each has different abilities, deciding which, if any, to use in a given situation is part of the challenge. These monsters, like Alisia herself, are fully upgradeable with power-ups. They can also die if weakened too much, forcing you to hunt for a reviving power-up. You can pause the game and select your companion at any time.Cheat: CodesWhen the Sega logo disappears hold A until the Game Arts logo vanishes. Now hold B until Gainax vanishes. Hold down C until Music Composed By disappears, and hold Start when the stars erupt from the crystal. Then during gameplay:</plot>
	<releasedate>23/3/1992</releasedate>
	<genre>Action</genre>
	<Developer>SEGA of America, Inc.</Developer>
	<nplayers>1</nplayers>
	<rating>3.8</rating>
	<VideoURL>ZIIRtWPYBtg</VideoURL>
	<thegamesdb_id>3486</thegamesdb_id>
	<gamefaqs_url>http://www.gamefaqs.com/genesis/586021-alisia-dragoon</gamefaqs_url>
	<mobygames_url>http://www.mobygames.com/game/genesis/alisia-dragoon</mobygames_url>
	<giantbomb_url>http://www.giantbomb.com/alisia-dragoon/3030-9988/</giantbomb_url>
	<boxart1>http://static.giantbomb.com/uploads/scale_large/9/93770/2368986-genesis_alisiadragoon_3.jpg</boxart1>
	<boxart2>http://i.imgur.com/YRwdYsQ.jpg</boxart2>
	<media>http://www.mobygames.com/images/covers/l/80578-alisia-dragoon-genesis-media.jpg</media>
	<snapshot1>http://www.mobygames.com/images/shots/l/63004-alisia-dragoon-genesis-screenshot-title-screen.jpg</snapshot1>
	<snapshot2>http://www.mobygames.com/images/shots/l/63005-alisia-dragoon-genesis-screenshot-the-top-menu-shows-the-statistics.jpg</snapshot2>
	<snapshot3>http://www.mobygames.com/images/shots/l/63006-alisia-dragoon-genesis-screenshot-power-ups-in-a-secret-area.jpg</snapshot3>
	<snapshot4>http://www.mobygames.com/images/shots/l/63007-alisia-dragoon-genesis-screenshot-wait-until-your-magic-gauge.jpg</snapshot4>
	<snapshot5>http://www.mobygames.com/images/shots/l/63008-alisia-dragoon-genesis-screenshot-ornah-baldour-s-aide-taunts.jpg</snapshot5>
	<snapshot6>http://www.mobygames.com/images/shots/l/63009-alisia-dragoon-genesis-screenshot-the-first-level-bosses.jpg</snapshot6>
	<snapshot7>http://www.mobygames.com/images/shots/l/63010-alisia-dragoon-genesis-screenshot-these-fairies-create-a-magic.jpg</snapshot7>
	<snapshot8>http://www.mobygames.com/images/shots/l/63011-alisia-dragoon-genesis-screenshot-the-second-level-boss.jpg</snapshot8>
	<snapshot9>http://www.mobygames.com/images/shots/l/63012-alisia-dragoon-genesis-screenshot-continue-screen.jpg</snapshot9>
	<snapshot10>http://www.mobygames.com/images/shots/l/63086-alisia-dragoon-genesis-screenshot-level-3-features-a-giant.jpg</snapshot10>
	<banner1>http://i.imgur.com/2wwfjWo.png</banner1>
	<clearlogo1>http://thegamesdb.net/banners/clearlogo/3486.png</clearlogo1>
	<Notes>The evil being Baldour is close to awakening from his long slumber with the help of his aide Ornah.  The world cannot bear a second revival of Baldour. Alisia Dragoon is the daughter of the mage that once contained Baldour.  Her father was tortured and killed before her very eyes when she was young. Alisia is now of age and possesses power that rivals her father.  Fueled by anger over his death and the desire for revenge, Alisia treks out to battle Baldour.</Notes>
	<boxart3>http://images.launchbox-app.com/68e994d3-c458-4b22-841b-19f134f5cf3b.jpg</boxart3>
	<boxart4>http://images.launchbox-app.com/4db249b2-c2b7-4704-976c-40260e8e16e6.jpg</boxart4>
	<boxart5>http://images.launchbox-app.com/fee13143-692c-4466-aef7-b5202f9123da.jpg</boxart5>
	<boxart6>http://images.launchbox-app.com/97d5d3f6-72b1-4012-88f1-65b859c13699.jpg</boxart6>
	<clearlogo2>http://images.launchbox-app.com/202a248d-d4fd-45f9-abca-50b6ffb12018.png</clearlogo2>
	<snapshot11>http://images.launchbox-app.com/49337b16-9567-497b-acd8-1b68a14ee182.jpg</snapshot11>
	<snapshot12>http://images.launchbox-app.com/f8d2328f-85ce-4c33-a7a1-1c96c7f27d9d.jpg</snapshot12>
	<snapshot13>http://images.launchbox-app.com/8982234f-0a5b-4eb6-9c7f-3f646238686f.jpg</snapshot13>
	<snapshot14>http://images.launchbox-app.com/a73c05e3-80c3-4cc3-9721-7dc9c21ca9d9.jpg</snapshot14>
	<snapshot15>http://images.launchbox-app.com/50389ae7-004c-4ff5-991c-628dde1bf7fe.jpg</snapshot15>
	<snapshot16>http://images.launchbox-app.com/9a377f54-b636-4085-bab5-f33a0a1fe60d.jpg</snapshot16>
	<snapshot17>http://images.launchbox-app.com/e19102e2-bf7f-42b6-a85c-dbd7165eca89.jpg</snapshot17>
	<snapshot18>http://images.launchbox-app.com/2877efb2-e7d1-480e-8976-055296fbb39d.jpg</snapshot18>
	<ESRB>T - Teen</ESRB>
	<Publisher>Game Arts</Publisher>
</game>