<Game>
	<Name>Ragnacenty (Korea)</Name>
	<plot>Crusader of Centy is a Role-Playing game, developed by NexTech and published by ATLUS,which was released in 1994.Cheat: Easy money Enter Rafflesia School (after seeing the king) and go to the first course. There are 4 Malins in the grass. Head north, go down the steps, and hit the right switch to reveal 6 Malins. Then leave (exit the school). Re-enter and repeat as desired. (10 coins a visit x # of visits = $$$)</plot>
	<releasedate>16/6/1994</releasedate>
	<genre>RPG, Action</genre>
	<Developer>NexTech</Developer>
	<nplayers>1</nplayers>
	<rating>7.6</rating>
	<VideoURL>dq7fDSYeM84</VideoURL>
	<thegamesdb_id>20574</thegamesdb_id>
	<gamefaqs_url>http://www.gamefaqs.com/genesis/586122-crusader-of-centy</gamefaqs_url>
	<boxart1>http://thegamesdb.net/banners/boxart/original/front/20574-1.jpg</boxart1>
	<boxart2>http://img.gamefaqs.net/box/2/3/1/47231_back.jpg</boxart2>
	<snapshot1>http://img.gamefaqs.net/screens/3/b/4/gfs_2138_1_1.jpg</snapshot1>
	<snapshot2>http://img.gamefaqs.net/screens/8/5/3/gfs_13489_2_1.jpg</snapshot2>
	<snapshot3>http://img.gamefaqs.net/screens/2/8/3/gfs_13489_2_2.jpg</snapshot3>
	<snapshot4>http://img.gamefaqs.net/screens/b/3/3/gfs_13489_2_3.jpg</snapshot4>
	<snapshot5>http://img.gamefaqs.net/screens/7/2/3/gfs_13489_2_4.jpg</snapshot5>
	<snapshot6>http://img.gamefaqs.net/screens/1/9/b/gfs_46719_2_1.jpg</snapshot6>
	<snapshot7>http://img.gamefaqs.net/screens/b/4/b/gfs_46719_2_2.jpg</snapshot7>
	<snapshot8>http://img.gamefaqs.net/screens/2/f/b/gfs_46719_2_3.jpg</snapshot8>
	<snapshot9>http://img.gamefaqs.net/screens/e/e/b/gfs_46719_2_4.jpg</snapshot9>
	<snapshot10>http://img.gamefaqs.net/screens/7/5/b/gfs_46719_2_5.jpg</snapshot10>
</game>